odoo/addons/iot_key_employee_rfid/README.rst
odoo/addons/iot_key_employee_rfid/__init__.py
odoo/addons/iot_key_employee_rfid/__manifest__.py
odoo/addons/iot_key_employee_rfid/i18n/iot_key_employee_rfid.pot
odoo/addons/iot_key_employee_rfid/i18n/it.po
odoo/addons/iot_key_employee_rfid/models/__init__.py
odoo/addons/iot_key_employee_rfid/models/hr_employee.py
odoo/addons/iot_key_employee_rfid/models/iot_key.py
odoo/addons/iot_key_employee_rfid/readme/CONTRIBUTORS.rst
odoo/addons/iot_key_employee_rfid/readme/DESCRIPTION.rst
odoo/addons/iot_key_employee_rfid/static/description/icon.png
odoo/addons/iot_key_employee_rfid/static/description/index.html
odoo/addons/iot_key_employee_rfid/tests/__init__.py
odoo/addons/iot_key_employee_rfid/tests/test_employee_rfid.py
odoo/addons/iot_key_employee_rfid/views/hr_employee.xml
odoo_addon_iot_key_employee_rfid-16.0.1.0.0.2.dist-info/METADATA
odoo_addon_iot_key_employee_rfid-16.0.1.0.0.2.dist-info/WHEEL
odoo_addon_iot_key_employee_rfid-16.0.1.0.0.2.dist-info/top_level.txt
odoo_addon_iot_key_employee_rfid-16.0.1.0.0.2.dist-info/RECORD
