Metadata-Version: 2.1
Name: odoo-addon-iot_key_employee_rfid
Version: 16.0.1.0.0.2
Summary: Use an Employee RFID Card as an IoT Key
Home-page: https://github.com/OCA/iot
Author: CreuBlanca,Odoo Community Association (OCA)
Author-email: support@odoo-community.org
License: AGPL-3
Classifier: Programming Language :: Python
Classifier: Framework :: Odoo
Classifier: Framework :: Odoo :: 16.0
Classifier: License :: OSI Approved :: GNU Affero General Public License v3
Requires-Python: >=3.10
Requires-Dist: odoo-addon-hr-attendance-rfid<16.1dev,>=16.0dev
Requires-Dist: odoo-addon-iot-rule<16.1dev,>=16.0dev
Requires-Dist: odoo<16.1dev,>=16.0a
